cumulus_library_suicidality_icd10/.sqlfluff
cumulus_library_suicidality_icd10/__init__.py
cumulus_library_suicidality_icd10/counts.py
cumulus_library_suicidality_icd10/counts.sql
cumulus_library_suicidality_icd10/define_age.sql
cumulus_library_suicidality_icd10/define_dx.sql
cumulus_library_suicidality_icd10/define_dx_attempt.sql
cumulus_library_suicidality_icd10/define_dx_attempt_snomed.sql
cumulus_library_suicidality_icd10/define_dx_ideation.sql
cumulus_library_suicidality_icd10/define_dx_self_harm.sql
cumulus_library_suicidality_icd10/define_note.sql
cumulus_library_suicidality_icd10/define_study_period.sql
cumulus_library_suicidality_icd10/manifest.toml
cumulus_library_suicidality_icd10/table_dx.sql
cumulus_library_suicidality_icd10/table_prevalence.sql
cumulus_library_suicidality_icd10/table_study_period.sql
cumulus_library_suicidality_icd10/valueset.py
cumulus_library_suicidality_icd10/valueset_dx_icd10_chip.tsv
cumulus_library_suicidality_icd10/valueset_dx_snomed_cste.json
cumulus_library_suicidality_icd10/version.sql
cumulus_library_suicidality_icd10-1.0.0.dist-info/WHEEL
cumulus_library_suicidality_icd10-1.0.0.dist-info/METADATA
cumulus_library_suicidality_icd10-1.0.0.dist-info/RECORD
