Metadata-Version: 2.3
Name: cumulus-library-suicidality-icd10
Version: 1.0.0
Summary: Validation of ICD-10 code usage of Suicidality Cases Compared to Patient Chart Review
Requires-Python: >= 3.11
Classifier: License :: OSI Approved :: Apache Software License
Classifier: Operating System :: OS Independent
Classifier: Programming Language :: Python :: 3
Classifier: Topic :: Software Development :: Libraries :: Python Modules
Requires-Dist: cumulus-library >= 3, <4
Requires-Dist: sqlfluff > 3
Requires-Dist: black ; extra == "dev"
Requires-Dist: pylint ; extra == "dev"
Project-URL: Documentation, https://docs.smarthealthit.org/cumulus/
Project-URL: Home, https://smarthealthit.org/cumulus-a-universal-sidecar-for-a-smart-learning-healthcare-system/
Project-URL: Source, https://github.com/smart-on-fhir/cumulus-library-suicidality-icd10
Provides-Extra: dev
